barbaric/__init__.py
barbaric/elements/svg.py
barbaric/types/protocols.py
barbaric-0.1.1.dist-info/METADATA
barbaric-0.1.1.dist-info/WHEEL
barbaric-0.1.1.dist-info/RECORD
