Metadata-Version: 2.1
Name: barbaric
Version: 0.1.1
Summary: A library for easily creating basic .SVG files.
Author: James Hudson
Author-email: james.hudson@outerbox.co.uk
Requires-Python: >=3.11,<4.0
Classifier: Programming Language :: Python :: 3
Classifier: Programming Language :: Python :: 3.11
